pytest_vcrpandas/__init__.py
pytest_vcrpandas-0.0.2.dist-info/AUTHORS
pytest_vcrpandas-0.0.2.dist-info/LICENSE
pytest_vcrpandas-0.0.2.dist-info/METADATA
pytest_vcrpandas-0.0.2.dist-info/WHEEL
pytest_vcrpandas-0.0.2.dist-info/entry_points.txt
pytest_vcrpandas-0.0.2.dist-info/pbr.json
pytest_vcrpandas-0.0.2.dist-info/top_level.txt
pytest_vcrpandas-0.0.2.dist-info/RECORD
