Metadata-Version: 2.1
Name: pytest-vcrpandas
Version: 0.0.2
Summary: Test from HTTP interactions to dataframe processed.
Home-page: https://github.com/gjeusel/pytest-vcrpandas
Author: See AUTHORS
Author-email: "guillaume.jeusel@gmail.com"
License: UNKNOWN
Platform: UNKNOWN
Classifier: Framework :: Pytest
Classifier: Development Status :: 4 - Beta
Classifier: Operating System :: MacOS :: MacOS X
Classifier: Operating System :: Microsoft :: Windows
Classifier: Operating System :: POSIX
Classifier: License :: OSI Approved :: MIT License
Classifier: Programming Language :: Python
Classifier: Programming Language :: Python :: 3.6
Requires-Dist: vcrpy
Requires-Dist: pandas
Requires-Dist: pytest
